xsmiles/__init__.py
xsmiles/_frontend.py
xsmiles/_version.py
xsmiles/widget.py
xsmiles/labextension/package.json
xsmiles/labextension/static/25.ab480dec851926bdaf86.js
xsmiles/labextension/static/480.7daa572c632e40d214ab.js
xsmiles/labextension/static/480.8b7a86744fc3157d3b06.js
xsmiles/labextension/static/568.00980f7515a845aa80d6.js
xsmiles/labextension/static/568.b566fc7e1f29ed367507.js
xsmiles/labextension/static/978.e1716316cb92e2cf15d8.js
xsmiles/labextension/static/978.e1716316cb92e2cf15d8.js.LICENSE.txt
xsmiles/labextension/static/remoteEntry.a8a19420609bce6a5ae1.js
xsmiles/labextension/static/remoteEntry.afd579499814b68cbf52.js
xsmiles/labextension/static/style.js
xsmiles/labextension/static/third-party-licenses.json
xsmiles/nbextension/extension.js
xsmiles/nbextension/index.js
xsmiles/nbextension/index.js.LICENSE.txt
xsmiles/nbextension/index.js.map
xsmiles/tests/__init__.py
xsmiles/tests/conftest.py
xsmiles/tests/test_example.py
xsmiles/tests/test_nbextension_path.py
xsmiles-0.2.2.data/data/etc/jupyter/nbconfig/notebook.d/xsmiles.json
xsmiles-0.2.2.data/data/share/jupyter/labextensions/xsmiles-ipywidget/install.json
xsmiles-0.2.2.data/data/share/jupyter/labextensions/xsmiles-ipywidget/package.json
xsmiles-0.2.2.data/data/share/jupyter/labextensions/xsmiles-ipywidget/static/480.8b7a86744fc3157d3b06.js
xsmiles-0.2.2.data/data/share/jupyter/labextensions/xsmiles-ipywidget/static/568.00980f7515a845aa80d6.js
xsmiles-0.2.2.data/data/share/jupyter/labextensions/xsmiles-ipywidget/static/978.e1716316cb92e2cf15d8.js
xsmiles-0.2.2.data/data/share/jupyter/labextensions/xsmiles-ipywidget/static/978.e1716316cb92e2cf15d8.js.LICENSE.txt
xsmiles-0.2.2.data/data/share/jupyter/labextensions/xsmiles-ipywidget/static/remoteEntry.a8a19420609bce6a5ae1.js
xsmiles-0.2.2.data/data/share/jupyter/labextensions/xsmiles-ipywidget/static/style.js
xsmiles-0.2.2.data/data/share/jupyter/labextensions/xsmiles-ipywidget/static/third-party-licenses.json
xsmiles-0.2.2.dist-info/LICENSE.txt
xsmiles-0.2.2.dist-info/METADATA
xsmiles-0.2.2.dist-info/WHEEL
xsmiles-0.2.2.dist-info/top_level.txt
xsmiles-0.2.2.dist-info/RECORD
